LICENSE.md
MANIFEST.in
README.md
setup.cfg
setup.py
foodalgo_uvicorn.egg-info/PKG-INFO
foodalgo_uvicorn.egg-info/SOURCES.txt
foodalgo_uvicorn.egg-info/dependency_links.txt
foodalgo_uvicorn.egg-info/entry_points.txt
foodalgo_uvicorn.egg-info/requires.txt
foodalgo_uvicorn.egg-info/top_level.txt
uvicorn/__init__.py
uvicorn/__main__.py
uvicorn/config.py
uvicorn/importer.py
uvicorn/logging.py
uvicorn/main.py
uvicorn/server.py
uvicorn/subprocess.py
uvicorn/workers.py
uvicorn/_handlers/__init__.py
uvicorn/_handlers/http.py
uvicorn/lifespan/__init__.py
uvicorn/lifespan/off.py
uvicorn/lifespan/on.py
uvicorn/loops/__init__.py
uvicorn/loops/asyncio.py
uvicorn/loops/auto.py
uvicorn/loops/uvloop.py
uvicorn/middleware/__init__.py
uvicorn/middleware/asgi2.py
uvicorn/middleware/debug.py
uvicorn/middleware/message_logger.py
uvicorn/middleware/proxy_headers.py
uvicorn/middleware/wsgi.py
uvicorn/protocols/__init__.py
uvicorn/protocols/utils.py
uvicorn/protocols/http/__init__.py
uvicorn/protocols/http/auto.py
uvicorn/protocols/http/flow_control.py
uvicorn/protocols/http/h11_impl.py
uvicorn/protocols/http/httptools_impl.py
uvicorn/protocols/websockets/__init__.py
uvicorn/protocols/websockets/auto.py
uvicorn/protocols/websockets/websockets_impl.py
uvicorn/protocols/websockets/wsproto_impl.py
uvicorn/supervisors/__init__.py
uvicorn/supervisors/basereload.py
uvicorn/supervisors/multiprocess.py
uvicorn/supervisors/statreload.py
uvicorn/supervisors/watchgodreload.py